lucterios/__init__.py
lucterios/documents/__init__.py
lucterios/documents/build
lucterios/documents/doc_editors.py
lucterios/documents/editors.py
lucterios/documents/ethercalc.py
lucterios/documents/models.py
lucterios/documents/models_legacy.py
lucterios/documents/test_tools.py
lucterios/documents/tests.py
lucterios/documents/views.py
lucterios/documents/assets/new.docx
lucterios/documents/assets/new.pptx
lucterios/documents/assets/new.xlsx
lucterios/documents/docs/build_en/doctrees/configuration.doctree
lucterios/documents/docs/build_en/doctrees/environment.pickle
lucterios/documents/docs/build_en/doctrees/index.doctree
lucterios/documents/docs/build_en/doctrees/shared_document.doctree
lucterios/documents/docs/build_fr/doctrees/configuration.doctree
lucterios/documents/docs/build_fr/doctrees/editor.doctree
lucterios/documents/docs/build_fr/doctrees/environment.pickle
lucterios/documents/docs/build_fr/doctrees/index.doctree
lucterios/documents/docs/build_fr/doctrees/shared_document.doctree
lucterios/documents/docs/en/Makefile
lucterios/documents/docs/en/conf.py
lucterios/documents/docs/en/configuration.png
lucterios/documents/docs/en/configuration.rst
lucterios/documents/docs/en/index.rst
lucterios/documents/docs/en/listdoc.png
lucterios/documents/docs/en/shared_document.rst
lucterios/documents/docs/en/showdoc.png
lucterios/documents/docs/fr/Makefile
lucterios/documents/docs/fr/conf.py
lucterios/documents/docs/fr/configuration.png
lucterios/documents/docs/fr/configuration.rst
lucterios/documents/docs/fr/editor.rst
lucterios/documents/docs/fr/ethercalc.png
lucterios/documents/docs/fr/etherpad.png
lucterios/documents/docs/fr/index.rst
lucterios/documents/docs/fr/listdoc.png
lucterios/documents/docs/fr/onlyoffice.png
lucterios/documents/docs/fr/shared_document.rst
lucterios/documents/docs/fr/showdoc.png
lucterios/documents/locale/en/LC_MESSAGES/django.mo
lucterios/documents/locale/en/LC_MESSAGES/django.po
lucterios/documents/locale/fr/LC_MESSAGES/django.mo
lucterios_documents-2.7.2.24102410.dist-info/LICENSE
lucterios_documents-2.7.2.24102410.dist-info/METADATA
lucterios_documents-2.7.2.24102410.dist-info/WHEEL
lucterios_documents-2.7.2.24102410.dist-info/top_level.txt
lucterios_documents-2.7.2.24102410.dist-info/RECORD
