Metadata-Version: 2.1
Name: lucterios-documents
Version: 2.7.2.24102410
Summary: documents managment module for Lucterios framework.
Home-page: http://www.lucterios.org
Author: Lucterios
Author-email: info@lucterios.org
License: GNU General Public License v3
Platform: Any
Classifier: Development Status :: 5 - Production/Stable
Classifier: Environment :: Web Environment
Classifier: Framework :: Django :: 4.2
Classifier: Intended Audience :: Developers
Classifier: Intended Audience :: End Users/Desktop
Classifier: License :: OSI Approved :: GNU General Public License v3 (GPLv3)
Classifier: Natural Language :: English
Classifier: Natural Language :: French
Classifier: Operating System :: OS Independent
Classifier: Programming Language :: Python :: 3.8
Classifier: Programming Language :: Python :: 3.9
Classifier: Programming Language :: Python :: 3.10
Classifier: Programming Language :: Python :: 3.11
Classifier: Programming Language :: Python :: 3.12
Classifier: Topic :: Database :: Front-Ends
License-File: LICENSE
Requires-Dist: lucterios ~=2.7
Requires-Dist: etherpad-lite ~=0.5
Requires-Dist: requests
Requires-Dist: mimetypes-magic ~=0.4
Requires-Dist: pdf2image ~=1.17
